mynetwork/__init__.py
mynetwork/cli.py
mynetwork/myip/__init__.py
mynetwork/myip/myip.py
mynetwork/speed/__init__.py
mynetwork/speed/speed.py
mynetwork-0.1.3.dist-info/WHEEL
mynetwork-0.1.3.dist-info/entry_points.txt
mynetwork-0.1.3.dist-info/METADATA
mynetwork-0.1.3.dist-info/RECORD
